main.py
myquerytutor/MQT_APP.sqlite
myquerytutor/MQT_EX.sqlite
myquerytutor/__init__.py
myquerytutor/__main__.py
myquerytutor/appsettings.py
myquerytutor/cli.py
myquerytutor/database_controller.py
myquerytutor/expectedresult.py
myquerytutor/expectedresult.ui
myquerytutor/first_run_wiz.py
myquerytutor/lessondialog.py
myquerytutor/lessondialog.ui
myquerytutor/mainwindow.py
myquerytutor/mainwindow.ui
myquerytutor/mqt.icns
myquerytutor/mqt.ico
myquerytutor/progressdialog.py
myquerytutor/server_sync.py
myquerytutor/settingsdialog.py
myquerytutor/settingsdialog.ui
myquerytutor/setup.py
myquerytutor/splash.png
myquerytutor/ui_expectedresult.py
myquerytutor/ui_lessondialog.py
myquerytutor/ui_mainwindow.py
myquerytutor/ui_settingsdialog.py
myquerytutor/watermark.png
myquerytutor/images/2mcgevm.jpg
myquerytutor/images/Australian_Coat_of_Arms.png
myquerytutor/images/ChinookERD.png
myquerytutor/images/Classified-Stamp.png
myquerytutor/images/SchoolERD.png
myquerytutor/images/VetERD.png
myquerytutor/images/WorldERD.png
myquerytutor/images/grunge.png
myquerytutor/images/map.jpeg
myquerytutor-2.1.1.dist-info/AUTHORS.rst
myquerytutor-2.1.1.dist-info/LICENSE
myquerytutor-2.1.1.dist-info/METADATA
myquerytutor-2.1.1.dist-info/WHEEL
myquerytutor-2.1.1.dist-info/entry_points.txt
myquerytutor-2.1.1.dist-info/top_level.txt
myquerytutor-2.1.1.dist-info/RECORD
