Metadata-Version: 2.1
Name: myquerytutor
Version: 2.1.1
Summary: Educational tool to teach SQL
Home-page: https://gitlab.com/tuxta/myquerytutor
Author: Steven Tucker
Author-email: tuxta2@gmail.com
License: LGPL-3.0-or-later
Project-URL: Changelog, https://gitlab.com/tuxta/myquerytutor/blob/master/CHANGELOG.rst
Project-URL: Issue Tracker, https://gitlab.com/tuxta/myquerytutor/issues
Platform: UNKNOWN
Classifier: Development Status :: 5 - Production/Stable
Classifier: Intended Audience :: Developers
Classifier: License :: OSI Approved :: GNU Lesser General Public License v3 or later (LGPLv3+)
Classifier: Operating System :: Unix
Classifier: Operating System :: POSIX
Classifier: Operating System :: Microsoft :: Windows
Classifier: Programming Language :: Python :: 3.6
Classifier: Programming Language :: Python :: 3.7
Classifier: Programming Language :: Python :: 3.8
Classifier: Programming Language :: Python :: 3.9
Classifier: Programming Language :: Python :: Implementation :: CPython
Classifier: Topic :: Utilities
Requires-Python: >=3.6, !=3.0.*, !=3.1.*, !=3.2.*, !=3.3.*, !=3.4.*, !=3.5.*
Requires-Dist: PyQt5 (>=5.13.1)
Requires-Dist: PyQtWebEngine (>=5.13.2)
Requires-Dist: beautifulsoup4 (>=4.8.2)
Requires-Dist: requests (>=2.20.1)
